function_table/__init__.py
function_table-0.2.0.dist-info/licenses/LICENSE
function_table-0.2.0.dist-info/METADATA
function_table-0.2.0.dist-info/WHEEL
function_table-0.2.0.dist-info/top_level.txt
function_table-0.2.0.dist-info/RECORD
