Metadata-Version: 2.4
Name: function-table
Version: 0.2.0
Summary: Learn a callable function from a table of inputs and outputs using XGBoost.
Author: Viethedev
License: MIT License
Project-URL: Homepage, https://github.com/Viethedev/function-table
Project-URL: Repository, https://github.com/Viethedev/function-table
Keywords: xgboost,function,table,regression
Classifier: Programming Language :: Python :: 3
Classifier: License :: OSI Approved :: MIT License
Classifier: Operating System :: OS Independent
Requires-Python: >=3.10
License-File: LICENSE
Requires-Dist: numpy>=2.0
Requires-Dist: xgboost>=3.0
Dynamic: license-file
